asmix/__init__.py
asmix/asmix.py
asmix-0.1.4.dist-info/METADATA
asmix-0.1.4.dist-info/WHEEL
asmix-0.1.4.dist-info/top_level.txt
asmix-0.1.4.dist-info/RECORD
