Metadata-Version: 2.1
Name: asmix
Version: 0.1.4
Summary: This is a library to check email Hotmail if is availabe, get instagram information by username, get reset of user instagram, check if email registered in instagram, And many more features that may be added soon.
Home-page: https://t.me/n1z1n
Author: Ilyass Asmix
Author-email: ilyassvv@gmail.com
Classifier: Programming Language :: Python :: 3
Classifier: License :: OSI Approved :: MIT License
Classifier: Operating System :: OS Independent
Requires-Python: >=3.6
Requires-Dist: requests
Requires-Dist: user_agent
